prism_rerun/__init__.py
prism_rerun/__main__.py
prism_rerun/prism_rerun.py
prism_rerun-0.0.40.dist-info/LICENSE
prism_rerun-0.0.40.dist-info/METADATA
prism_rerun-0.0.40.dist-info/WHEEL
prism_rerun-0.0.40.dist-info/entry_points.txt
prism_rerun-0.0.40.dist-info/top_level.txt
prism_rerun-0.0.40.dist-info/RECORD
