Metadata-Version: 2.1
Name: prism-rerun
Version: 0.0.40
Summary: UNKNOWN
Home-page: UNKNOWN
Author: Ashwin Kumar
Author-email: <ashwinkumar@chargebee.com>
License: UNKNOWN
Platform: UNKNOWN
Classifier: Development Status :: 1 - Planning
Classifier: Intended Audience :: Developers
Classifier: Programming Language :: Python :: 3
Classifier: Operating System :: Unix
Classifier: Operating System :: MacOS :: MacOS X
Classifier: Operating System :: Microsoft :: Windows
